{
    "date": "2026-07-20",
    "top_5_trending": [
        {
            "repo": "/tirth8205/code-review-graph",
            "description": "暂无描述",
            "stars_today": "663 stars today",
            "url": "https://github.com/tirth8205/code-review-graph"
        },
        {
            "repo": "/kvcache-ai/ktransformers",
            "description": "暂无描述",
            "stars_today": "360 stars today",
            "url": "https://github.com/kvcache-ai/ktransformers"
        },
        {
            "repo": "/rohitg00/ai-engineering-from-scratch",
            "description": "暂无描述",
            "stars_today": "501 stars today",
            "url": "https://github.com/rohitg00/ai-engineering-from-scratch"
        },
        {
            "repo": "/jamiepine/voicebox",
            "description": "暂无描述",
            "stars_today": "610 stars today",
            "url": "https://github.com/jamiepine/voicebox"
        },
        {
            "repo": "/KnockOutEZ/wigolo",
            "description": "暂无描述",
            "stars_today": "595 stars today",
            "url": "https://github.com/KnockOutEZ/wigolo"
        }
    ]
}